tf2.py
tf2_api-0.0.1.data/scripts/tf2.py
tf2_api-0.0.1.dist-info/METADATA
tf2_api-0.0.1.dist-info/WHEEL
tf2_api-0.0.1.dist-info/top_level.txt
tf2_api-0.0.1.dist-info/RECORD
