Metadata-Version: 2.1
Name: tf2-api
Version: 0.0.1
Summary: A simple api to get player stats for TF2
Home-page: https://github.com/DevHollo/tf2-api/
Author: Hollo
Author-email: hollo1234567890e@gmail.com
Requires-Dist: requests ==2.31.0
